argteller/__init__.py
argteller/builder/__init__.py
argteller/builder/access_object.py
argteller/builder/get_control_panel.py
argteller/decorators/__init__.py
argteller/decorators/class_decorator.py
argteller/decorators/method_decorator.py
argteller/tree/__init__.py
argteller/tree/tree_builder.py
argteller/tree/tree_node.py
argteller/tree/tree_parser.py
argteller/utils/__init__.py
argteller/utils/data_structure_utils.py
argteller/widgets/__init__.py
argteller/widgets/dynamic_switch.py
argteller/widgets/dynamic_widgets.py
argteller/widgets/widgets.py
argteller_viz-0.0b45.dist-info/LICENSE
argteller_viz-0.0b45.dist-info/METADATA
argteller_viz-0.0b45.dist-info/WHEEL
argteller_viz-0.0b45.dist-info/top_level.txt
argteller_viz-0.0b45.dist-info/RECORD
