Metadata-Version: 2.1
Name: argteller-viz
Version: 0.0b45
Summary: Decorator for stylized interactive constructor using DSL parser
Home-page: https://github.com/mozjay0619/argteller-viz
Author: Jay Kim
Author-email: mozjay0619@gmail.com
License: DSB 3-clause
Platform: UNKNOWN
Requires-Python: >=3
License-File: LICENSE
